dbrief/__init__.py
dbrief/report.py
dbrief/templates/default.html
demo/demo.py
docs/source/conf.py
tests/__init__.py
tests/conftest.py
dbrief-0.1.2.dist-info/LICENSE.txt
dbrief-0.1.2.dist-info/METADATA
dbrief-0.1.2.dist-info/WHEEL
dbrief-0.1.2.dist-info/top_level.txt
dbrief-0.1.2.dist-info/RECORD
